LICENSE
MANIFEST.in
README.md
pyproject.toml
setup.py
./trackstar/core/covariance_matrix.pyx
./trackstar/core/datum.pyx
./trackstar/core/matrix.pyx
./trackstar/core/multithread.pyx
./trackstar/core/sample.pyx
./trackstar/core/track.pyx
./trackstar/core/utils.pyx
./trackstar/core/src/datum.c
./trackstar/core/src/likelihood.c
./trackstar/core/src/matrix.c
./trackstar/core/src/quadrature.c
./trackstar/core/src/sample.c
./trackstar/core/src/track.c
./trackstar/core/src/utils.c
docs/src/conf.py
docs/src/benchmarks/__main__.py
docs/src/benchmarks/common.py
docs/src/benchmarks/dimensionality.py
docs/src/benchmarks/nthreads.py
docs/src/benchmarks/samplesize.py
docs/src/benchmarks/tracksize.py
trackstar/__init__.py
trackstar/exceptions.py
trackstar/version.py
trackstar.egg-info/PKG-INFO
trackstar.egg-info/SOURCES.txt
trackstar.egg-info/dependency_links.txt
trackstar.egg-info/requires.txt
trackstar.egg-info/top_level.txt
trackstar/benchmarks/__init__.py
trackstar/benchmarks/__main__.py
trackstar/benchmarks/benchmark.py
trackstar/benchmarks/discovery.py
trackstar/core/__init__.py
trackstar/core/covariance_matrix.pxd
trackstar/core/covariance_matrix.pyx
trackstar/core/datum.pxd
trackstar/core/datum.pyx
trackstar/core/matrix.pxd
trackstar/core/matrix.pyx
trackstar/core/multithread.pxd
trackstar/core/multithread.pyx
trackstar/core/sample.pxd
trackstar/core/sample.pyx
trackstar/core/track.pxd
trackstar/core/track.pyx
trackstar/core/utils.pxd
trackstar/core/utils.pyx
trackstar/core/benchmarks/__init__.py
trackstar/core/benchmarks/benchmark_covariance_matrix.py
trackstar/core/benchmarks/benchmark_datum.py
trackstar/core/benchmarks/benchmark_matrix.py
trackstar/core/src/datum.c
trackstar/core/src/datum.h
trackstar/core/src/debug.h
trackstar/core/src/likelihood.c
trackstar/core/src/likelihood.h
trackstar/core/src/matrix.c
trackstar/core/src/matrix.h
trackstar/core/src/multithread.h
trackstar/core/src/quadrature.c
trackstar/core/src/quadrature.h
trackstar/core/src/sample.c
trackstar/core/src/sample.h
trackstar/core/src/track.c
trackstar/core/src/track.h
trackstar/core/src/utils.c
trackstar/core/src/utils.h
trackstar/core/tests/__init__.py
